git_repo_organizer/__init__.py
git_repo_organizer/cli.py
git_repo_organizer/config.py
git_repo_organizer/database.py
git_repo_organizer/main.py
git_repo_organizer/repo_organizer.py
ptermtools-0.1.0.dist-info/LICENSE
ptermtools-0.1.0.dist-info/WHEEL
ptermtools-0.1.0.dist-info/METADATA
ptermtools-0.1.0.dist-info/RECORD
