Metadata-Version: 2.1
Name: ptermtools
Version: 0.1.0
Summary: pgierz's organizational tools
License: GPL-2.0-or-later
Author: Paul Gierz
Author-email: paulgierz@gmail.com
Requires-Python: >=3.7,<4.0
Classifier: License :: OSI Approved :: GNU General Public License v2 or later (GPLv2+)
Classifier: Programming Language :: Python :: 3
Classifier: Programming Language :: Python :: 3.10
Classifier: Programming Language :: Python :: 3.7
Classifier: Programming Language :: Python :: 3.8
Classifier: Programming Language :: Python :: 3.9
Requires-Dist: PyGithub (>=1.55,<2.0)
Requires-Dist: click8 (>=8.0.1,<9.0.0)
Requires-Dist: docker (>=5.0.3,<6.0.0)
Requires-Dist: fs (>=2.4.14,<3.0.0)
Requires-Dist: python-gitlab (>=2.10.1,<3.0.0)
Requires-Dist: spython (>=0.1.17,<0.2.0)
